quark/BenchmarkManager.py
quark/BenchmarkRecord.py
quark/ConfigManager.py
quark/Installer.py
quark/Metrics.py
quark/Plotter.py
quark/__init__.py
quark/__main__.py
quark/quark.py
quark/utils.py
quark/utils_mpi.py
quark/demo/instruction_demo.py
quark/modules/Core.py
quark/modules/__init__.py
quark/modules/applications/Application.py
quark/modules/applications/Mapping.py
quark/modules/applications/__init__.py
quark/modules/applications/optimization/Optimization.py
quark/modules/applications/optimization/__init__.py
quark/modules/applications/optimization/ACL/ACL.py
quark/modules/applications/optimization/ACL/__init__.py
quark/modules/applications/optimization/ACL/mappings/ISING.py
quark/modules/applications/optimization/ACL/mappings/QUBO.py
quark/modules/applications/optimization/ACL/mappings/__init__.py
quark/modules/applications/optimization/MIS/MIS.py
quark/modules/applications/optimization/MIS/__init__.py
quark/modules/applications/optimization/MIS/data/__init__.py
quark/modules/applications/optimization/MIS/data/graph_layouts.py
quark/modules/applications/optimization/MIS/mappings/NeutralAtom.py
quark/modules/applications/optimization/MIS/mappings/QIRO.py
quark/modules/applications/optimization/MIS/mappings/__init__.py
quark/modules/applications/optimization/PVC/PVC.py
quark/modules/applications/optimization/PVC/__init__.py
quark/modules/applications/optimization/PVC/data/createReferenceGraph.py
quark/modules/applications/optimization/PVC/data/reference_graph.gpickle
quark/modules/applications/optimization/PVC/mappings/ISING.py
quark/modules/applications/optimization/PVC/mappings/QUBO.py
quark/modules/applications/optimization/PVC/mappings/__init__.py
quark/modules/applications/optimization/SAT/SAT.py
quark/modules/applications/optimization/SAT/__init__.py
quark/modules/applications/optimization/SAT/mappings/ChoiISING.py
quark/modules/applications/optimization/SAT/mappings/ChoiQUBO.py
quark/modules/applications/optimization/SAT/mappings/DinneenISING.py
quark_famework-0.1.dist-info/AUTHORS
quark_famework-0.1.dist-info/LICENSE
quark_famework-0.1.dist-info/METADATA
quark_famework-0.1.dist-info/NOTICE
quark_famework-0.1.dist-info/WHEEL
quark_famework-0.1.dist-info/top_level.txt
quark_famework-0.1.dist-info/RECORD
