Metadata-Version: 2.2
Name: quark-famework
Version: 0.1
Summary: Framework for Quantum Computing Application Benchmarking
Author-email: Philipp Ross <philipp.ross@bmw.de>, Marvin Erdmann <marvin.erdmann@bmw.de>, Andre Luckow <andre.luckow@bmwgroup.com>, Greshma Shaji <greshma.shaji@bmwgroup.com>, Florian Kiwit <florian.kiwit@bmw.de>, Benjamin Decker <benjamin.decker@bmw.de>
License: Apache-2.0
Project-URL: Homepage, https://github.com/QUARK-framework/QUARK
Project-URL: Issues, https://github.com/QUARK-framework/QUARK/issues
Classifier: Programming Language :: Python :: 3
Classifier: Operating System :: OS Independent
Requires-Python: >=3.12
License-File: LICENSE
License-File: NOTICE
License-File: AUTHORS
Requires-Dist: amazon-braket-pennylane-plugin==1.30.2
Requires-Dist: amazon-braket-sdk==1.88.2
Requires-Dist: boto3==1.35.73
Requires-Dist: botocore==1.35.73
Requires-Dist: cma==4.0.0
Requires-Dist: dimod==0.12.18
Requires-Dist: dwave-networkx==0.8.15
Requires-Dist: dwave-samplers==1.4.0
Requires-Dist: inquirer==3.4.0
Requires-Dist: jax==0.4.35
Requires-Dist: jaxlib==0.4.35
Requires-Dist: matplotlib==3.9.3
Requires-Dist: more-itertools==10.5.0
Requires-Dist: networkx==3.4.2
Requires-Dist: nnf==0.4.1
Requires-Dist: numpy==1.26.4
Requires-Dist: openpyxl==3.1.5
Requires-Dist: packaging==24.2
Requires-Dist: pandas==2.2.3
Requires-Dist: pennylane==0.39.0
Requires-Dist: pennylane-lightning==0.39.0
Requires-Dist: pulp==2.9.0
Requires-Dist: pulser==1.1.1
Requires-Dist: python-sat==1.8.dev13
Requires-Dist: pyyaml==6.0.2
Requires-Dist: qiskit==1.3.0
Requires-Dist: qiskit-aer==0.15.1
Requires-Dist: qiskit-algorithms==0.3.1
Requires-Dist: qiskit-ibm-runtime==0.33.2
Requires-Dist: qiskit-optimization==0.6.1
Requires-Dist: qrisp==0.5.2
Requires-Dist: qubovert==1.2.5
Requires-Dist: scipy==1.12.0
Requires-Dist: seaborn==0.13.2
Requires-Dist: sphinx==8.1.3
Requires-Dist: sphinx-rtd-theme==3.0.2
Requires-Dist: tensorboard==2.18.0
Requires-Dist: tensorboardx==2.6.2.2
Requires-Dist: torch==2.5.1
Requires-Dist: typing-extensions==4.12.2
Provides-Extra: dev
Requires-Dist: setuptools>=61.0; extra == "dev"
